example/__init__.py
example/decrypt.py
example/decrypt_file.py
example/encrypt.py
example/encrypt_file.py
example/generate_keys.py
secrets_manager/__init__.py
secrets_manager/decrypt.py
secrets_manager/encrypt.py
secrets_manager/generate_keys.py
secrets_manager/settings.py
tests/__init__.py
tests/decrypt.py
tests/encrypt.py
tests/generate_keys.py
asm_secrets_manager-1.0.1.dist-info/AUTHORS
asm_secrets_manager-1.0.1.dist-info/LICENSE
asm_secrets_manager-1.0.1.dist-info/METADATA
asm_secrets_manager-1.0.1.dist-info/WHEEL
asm_secrets_manager-1.0.1.dist-info/top_level.txt
asm_secrets_manager-1.0.1.dist-info/RECORD
